{
    "success":true,
    "data":[{
        "id":1,
        "title":"强烈分享5本熬夜也要看完的好书！",
        "content":"<p className='bold'>极其强烈推荐5本爱不释手的好书，每本都是压箱底的神作。</p><br/><p>它们不仅懂我，还给了我很多启发，是我成长路上必不可少的闲时陪伴。</p><br/><p className='bold'>现在分享给大家，希望也能对你们有所帮助，喜欢的同学别忘了点赞收藏哦~</p><br/><h3>1、《局外人》</h3><img src='https://upload-images.jianshu.io/upload_images/5078275-ff71f1e9dabfaa2b.jpg?imageMogr2/auto-orient/strip|imageView2/2/w/720/format/webp' alt=''/><br/><p className='bold'>在以我为主角的法庭上，我却成了局外人。</p><br/><p>这是法国作家加缪的代表作之一。</p><br/><p className='bold'>本书以第一人称叙述，在妈妈葬礼、一次度假中偶然开枪打死的人，以及主人公自身的三场死亡中展现了残酷的社会准则，法庭上决定主人公命运的不是案件的客观事实，而是人们对他的看法。</p><br/><p>“今天，妈妈死了。也许是昨天，我不知道。”</p><br/><p className='bold'>这是小说开头的第一句话，短短几个字向我们展现了主人公无比冷漠的形象，吸引着人往下读，也通过他的形象揭示了世界的荒谬。</p><br/><p>不禁让我想到我们的“后真相时代”：人们对于个人态度、立场、情绪的关注远超过事实本身，真相变得次要。</p><br/><p>这本书给我留下了许多生活的思考，值得一看！</p><br/><h3>2、《查令十字街84号》</h3><img src='https://upload-images.jianshu.io/upload_images/5078275-8527a49748086390.jpg?imageMogr2/auto-orient/strip|imageView2/2/w/720/format/webp' alt=''/><br/><p>“但是，书店还在那儿，你们若恰好经过查令十字街84号，代我献上一吻，我亏欠它良多......”</p><br/><p className='bold'>起初见到这个书名，我以为是侦探悬疑类小说，但没想到它就是英国一家旧书店的地址，而书里的内容也是温馨幽默的。</p><br/><p >这是位于纽约的作家与书店长达二十年的通信记录，是一段跨越时间与空间的温暖情谊。</p><br/><p className='bold'>作家不仅通过书信来购买书本，还经常在节假日给书店职工寄去小礼物，大家的感情也变得越来越深。在网购不断发展，实体书店难以生存的现在，这本书又勾起了我对过去生活方式的留恋。</p><br/><p >书的内容比较简短，读起来很轻松，是小憩时想要看书的不错选择。</p><br/><h3>3、《情书》</h3><img src='https://upload-images.jianshu.io/upload_images/5078275-0ca81a887c6a2df3.jpg?imageMogr2/auto-orient/strip|imageView2/2/w/720/format/webp' alt=''/><br/><p>“暗恋”应该是每个人学生时代都逃不过的话题，关于暗恋的作品也有很多，而最让我触动的还是这本《情书》。</p><br/><p className='bold'>此书讲的是一位叫渡边博子的女生在未婚夫藤井树过世两周年忌日时偶然发现他读中学时家的住址，那个地方现在已经变成了公路。</p><br/><p >她因为怀念而寄去了一封信，本只是想寄托自己的哀思，却没想到收到了回信。</p><br/><p>其实这是另一位叫藤井树的同名同姓的女孩寄来的，男藤井树与女藤井树在中学时是同班同学，随着两位女生的通信，一个尘封已久的暗恋故事逐渐展开。</p><br/><p className='bold'>《情书》不只讲了爱情，它还关乎到死亡。</p><br/><p >男藤井树的死亡，女藤井树爸爸的死亡。作者想向我们传达的是所爱之人确实不在了，但关于他们的美好回忆、他们的感情、他们的灵魂，其实已经永远留存在我们的心中。</p><br/><p >现实生活中很少有像这样同名同姓的巧合，可是大多数人的暗恋故事就是这样苦涩而美好，我认为作家岩井俊二把这种缺憾美表现的极致。</p><br/><p className='bold'>这本书同时也被作家改编成了同名电影，成为日本爱情电影的经典</p><br/><p>（想看的同学点赞告诉我~）</p>"
    },{
        "id":2,
        "title":"second",
        "content":"2"
    }]
}